testing_cookiecutter/__init__.py
testing_cookiecutter/sounds_generator.py
testing_cookiecutter-0.1.1.dist-info/LICENSE
testing_cookiecutter-0.1.1.dist-info/METADATA
testing_cookiecutter-0.1.1.dist-info/WHEEL
testing_cookiecutter-0.1.1.dist-info/top_level.txt
testing_cookiecutter-0.1.1.dist-info/RECORD
