Metadata-Version: 2.1
Name: testing-cookiecutter
Version: 0.1.1
Summary: testing on an opinionated, minimal cookiecutter template for Python packages
Home-page: https://github.com/TrainTravel/testing_pypackaging.git
Author: Train Chen
Author-email: train981316@gmail.com
License: MIT
Platform: UNKNOWN
Classifier: Development Status :: 2 - Pre-Alpha
Classifier: License :: OSI Approved :: MIT License
Classifier: Programming Language :: Python
Classifier: Programming Language :: Python :: 3
Classifier: Programming Language :: Python :: 3.6
Classifier: Programming Language :: Python :: 3.7
